setup.py
nsm/__init__.py
nsm.egg-info/PKG-INFO
nsm.egg-info/SOURCES.txt
nsm.egg-info/dependency_links.txt
nsm.egg-info/not-zip-safe
nsm.egg-info/top_level.txt