Metadata-Version: 1.0
Name: nsm
Version: 0.1
Summary: A NS-3 Simulation Manager
Home-page: http://github.com/rgrunbla/nsm
Author: Rémy Grünblatt
Author-email: remy@grunblatt.org
License: MIT
Platform: UNKNOWN
